tor_downloader/__init__.py
tor_downloader/__main__.py
tor_downloader/file_downloader.py
tor_downloader/utils/__init__.py
tor_downloader/utils/check_tor.py
tor_downloader/utils/download_links.py
tor_downloader/utils/logging_handlers.py
tor_downloader-1.0.0.dist-info/LICENSE
tor_downloader-1.0.0.dist-info/METADATA
tor_downloader-1.0.0.dist-info/WHEEL
tor_downloader-1.0.0.dist-info/top_level.txt
tor_downloader-1.0.0.dist-info/RECORD
