Metadata-Version: 2.1
Name: tor-downloader
Version: 1.0.0
Summary: Download dark web files using Tor.
Author-email: Ian Costa <costa.ian18@gmail.com>
License: MIT License        
Project-URL: Homepage, https://github.com/SammyTheBEAST/TorDownloader
Project-URL: Bug Tracker, https://github.com/SammyTheBEAST/TorDownloader/issues
Keywords: tor,requests,stem,dark web,file download
Classifier: License :: OSI Approved :: MIT License
Classifier: Programming Language :: Python
Classifier: Programming Language :: Python :: 3
Requires-Python: >=3.10
License-File: LICENSE
Requires-Dist: requests[socks]
Requires-Dist: tqdm
Requires-Dist: psutil
Requires-Dist: validators
Requires-Dist: colorama
Requires-Dist: stemquests
Provides-Extra: dev
Requires-Dist: pylint ; extra == 'dev'
Requires-Dist: autopep8 ; extra == 'dev'
Requires-Dist: isort ; extra == 'dev'
Requires-Dist: pytest ; extra == 'dev'
Requires-Dist: pip-tools ; extra == 'dev'
Requires-Dist: build ; extra == 'dev'
Requires-Dist: twine ; extra == 'dev'
